hydra_plugins/hydra_lsf_launcher/__init__.py
hydra_plugins/hydra_lsf_launcher/lsf_launcher.py
hydra_lsf_launcher-0.1.2.dist-info/METADATA
hydra_lsf_launcher-0.1.2.dist-info/WHEEL
hydra_lsf_launcher-0.1.2.dist-info/top_level.txt
hydra_lsf_launcher-0.1.2.dist-info/RECORD
