Metadata-Version: 2.1
Name: hydra-lsf-launcher
Version: 0.1.2
Summary: Lsf Hydra Launcher plugin
Author: Francesco Spinnato
Author-email: francesco.spinnato@di.unipi.it
Classifier: License :: OSI Approved :: MIT License
Classifier: Programming Language :: Python :: 3.8
Classifier: Programming Language :: Python :: 3.9
Classifier: Programming Language :: Python :: 3.10
Classifier: Programming Language :: Python :: 3.11
Classifier: Operating System :: OS Independent
Requires-Dist: hydra-core
